opedia_dataset_validator/__init__.py
opedia_dataset_validator/_version.py
opedia_dataset_validator/cli.py
opedia_dataset_validator/dataset_file_def.yaml
opedia_dataset_validator/error.py
opedia_dataset_validator/printer.py
opedia_dataset_validator/validator.py
opedia_dataset_validator-0.3.10.dist-info/LICENSE.txt
opedia_dataset_validator-0.3.10.dist-info/METADATA
opedia_dataset_validator-0.3.10.dist-info/RECORD
opedia_dataset_validator-0.3.10.dist-info/WHEEL
opedia_dataset_validator-0.3.10.dist-info/entry_points.txt
opedia_dataset_validator-0.3.10.dist-info/top_level.txt
