Metadata-Version: 2.1
Name: opedia-dataset-validator
Version: 0.3.10
Summary: A tool to validate Opedia dataset files.
Home-page: https://github.com/ctberthiaume/opedia_dataset_validator
Author: Chris T. Berthiaume
Author-email: chrisbee@uw.edu
License: LICENSE.txt
Download-URL: https://github.com/ctberthiaume/opedia_dataset_validator/archive/0.3.10.tar.gz
Keywords: opedia,validator
Platform: any
Classifier: Development Status :: 4 - Beta
Classifier: Environment :: Console
Classifier: Intended Audience :: Science/Research
Classifier: Topic :: Scientific/Engineering
Classifier: License :: OSI Approved :: MIT License
Classifier: Programming Language :: Python :: 2
Classifier: Programming Language :: Python :: 2.7
Classifier: Programming Language :: Python :: 3
Requires-Python: >=2.6, <4
Requires-Dist: arrow
Requires-Dist: click
Requires-Dist: oyaml
Requires-Dist: pandas (<=0.22.0,>=0.21.0)
Requires-Dist: xlrd
